{"id": 3053, "word": ["流", "不", "沉", "默", "寡", "言", "可", "痼", "蜚", "造", "跋", "扈", "自", "恣", "语", "无", "伦", "次", "山", "若", "涉", "既", "一", "水", "到", "渠", "成", "无", "边", "无", "际", "事", "所", "实", "事", "求", "是"], "idiom": ["跋扈自恣", "沉痼自若", "沉默寡言", "流言蜚语", "语无伦次", "不可造次", "跋山涉水", "水到渠成", "既成事实", "实事求是", "一无所求", "无边无际"], "posx": [5, 8, 2, 3, 4, 5, 8, 2, 5, 8, 0, 1, 2, 3, 5, 6, 7, 8, 0, 2, 0, 3, 5, 0, 1, 2, 3, 5, 6, 7, 8, 3, 5, 3, 4, 5, 6], "posy": [8, 8, 7, 7, 7, 7, 7, 6, 6, 6, 5, 5, 5, 5, 5, 5, 5, 5, 4, 4, 3, 3, 3, 2, 2, 2, 2, 2, 2, 2, 2, 1, 1, 0, 0, 0, 0], "answer": [0, 1, 2, 3, 4, 6, 8, 10, 12, 13, 14, 15, 17, 18, 19, 20, 21, 22, 24, 25, 26, 28, 29, 30, 31, 32, 34, 35, 36], "barrier": []}