{"id": 4604, "word": ["不", "含", "糊", "其", "辞", "枉", "苞", "而", "费", "坐", "以", "待", "毙", "别", "出", "心", "裁", "吃", "放", "机", "山", "玩", "空", "洞", "无", "物", "丧", "宏", "图", "大", "志"], "idiom": ["坐以待毙", "含苞待放", "含糊其辞", "不辞而别", "别出心裁", "枉费心机", "坐吃山空", "空洞无物", "玩物丧志", "宏图大志"], "posx": [5, 2, 3, 4, 5, 7, 2, 5, 7, 0, 1, 2, 3, 5, 6, 7, 8, 0, 2, 7, 0, 3, 0, 1, 2, 3, 3, 0, 1, 2, 3], "posy": [8, 7, 7, 7, 7, 7, 6, 6, 6, 5, 5, 5, 5, 5, 5, 5, 5, 4, 4, 4, 3, 3, 2, 2, 2, 2, 1, 0, 0, 0, 0], "answer": [0, 1, 2, 3, 5, 7, 8, 9, 10, 11, 13, 14, 15, 17, 18, 20, 21, 23, 24, 25, 27, 28, 30], "barrier": []}