{"id": 3746, "word": ["百", "百", "花", "甲", "之", "年", "齐", "大", "步", "流", "星", "放", "计", "罗", "千", "棋", "天", "下", "一", "家", "开", "诚", "布", "公", "涯", "万", "门", "海", "门", "户", "之", "见", "角", "山"], "idiom": ["天涯海角", "天下一家", "千家万户", "门户之见", "开门见山", "开诚布公", "星罗棋布", "大步流星", "百年大计", "花甲之年", "百花齐放"], "posx": [1, 4, 1, 2, 3, 4, 1, 4, 5, 6, 7, 1, 4, 7, 3, 7, 0, 1, 2, 3, 5, 6, 7, 8, 0, 3, 5, 0, 2, 3, 4, 5, 0, 5], "posy": [8, 8, 7, 7, 7, 7, 6, 6, 6, 6, 6, 5, 5, 5, 4, 4, 3, 3, 3, 3, 3, 3, 3, 3, 2, 2, 2, 1, 1, 1, 1, 1, 0, 0], "answer": [0, 1, 3, 4, 5, 6, 8, 9, 10, 11, 12, 13, 14, 15, 16, 18, 19, 20, 21, 23, 24, 25, 26, 27, 28, 30, 31], "barrier": []}