{"id": 4080, "word": ["合", "二", "为", "一", "兵", "表", "戎", "吉", "人", "天", "相", "不", "才", "见", "多", "识", "广", "走", "好", "全", "为", "非", "作", "歹", "心", "上", "壁", "万", "全", "之", "策", "上", "意", "观"], "idiom": ["全心全意", "万全之策", "走为上策", "为非作歹", "不识好歹", "见多识广", "兵戎相见", "吉人天相", "一表人才", "合二为一", "作壁上观"], "posx": [0, 1, 2, 3, 5, 3, 5, 2, 3, 4, 5, 7, 3, 5, 6, 7, 8, 4, 7, 2, 4, 5, 6, 7, 2, 4, 6, 1, 2, 3, 4, 6, 2, 6], "posy": [8, 8, 8, 8, 8, 7, 7, 6, 6, 6, 6, 6, 5, 5, 5, 5, 5, 4, 4, 3, 3, 3, 3, 3, 2, 2, 2, 1, 1, 1, 1, 1, 0, 0], "answer": [2, 3, 5, 9, 10, 13, 14, 18, 19, 21, 23, 24, 25, 29, 30, 33], "barrier": []}