{"id": 5384, "word": ["见", "死", "不", "救", "遇", "气", "风", "行", "水", "上", "沉", "鱼", "落", "雁", "架", "沉", "过", "河", "拆", "桥", "拔", "吹", "毛", "求", "疵", "灰", "全", "之", "责", "力", "备"], "idiom": ["吹灰之力", "吹毛求疵", "雁过拔毛", "沉鱼落雁", "死气沉沉", "见死不救", "过河拆桥", "遇水架桥", "风行水上", "求全责备"], "posx": [0, 1, 2, 3, 7, 1, 5, 6, 7, 8, 1, 2, 3, 4, 7, 1, 4, 5, 6, 7, 4, 3, 4, 5, 6, 3, 5, 3, 5, 3, 5], "posy": [8, 8, 8, 8, 8, 7, 7, 7, 7, 7, 6, 6, 6, 6, 6, 5, 5, 5, 5, 5, 4, 3, 3, 3, 3, 2, 2, 1, 1, 0, 0], "answer": [0, 2, 3, 5, 6, 7, 8, 10, 11, 12, 14, 15, 16, 17, 19, 20, 21, 22, 24, 25, 26, 27, 28, 30], "barrier": []}