{"id": 5281, "word": ["精", "忠", "心", "耿", "耿", "报", "举", "国", "上", "下", "直", "抒", "胸", "臆", "不", "无", "信", "以", "为", "真", "点", "睛", "之", "笔", "例", "墨", "涂", "鸦", "雀", "无", "声"], "idiom": ["忠心耿耿", "精忠报国", "举国上下", "下不为例", "信以为真", "信笔涂鸦", "鸦雀无声", "点睛之笔", "胸无点墨", "直抒胸臆"], "posx": [5, 5, 6, 7, 8, 5, 4, 5, 6, 7, 0, 1, 2, 3, 7, 2, 5, 6, 7, 8, 2, 3, 4, 5, 7, 2, 5, 5, 6, 7, 8], "posy": [8, 7, 7, 7, 7, 6, 5, 5, 5, 5, 4, 4, 4, 4, 4, 3, 3, 3, 3, 3, 2, 2, 2, 2, 2, 1, 1, 0, 0, 0, 0], "answer": [0, 2, 3, 4, 5, 6, 7, 8, 10, 12, 13, 14, 15, 16, 18, 19, 21, 22, 23, 24, 25, 27, 29, 30], "barrier": []}