{"id": 309, "word": ["碧", "呕", "心", "沥", "血", "比", "丹", "置", "劈", "天", "心", "腹", "之", "患", "风", "急", "浪", "高", "不", "斩", "蛮", "横", "无", "理", "浪", "恶", "不", "为", "非", "作", "歹"], "idiom": ["为非作歹", "无恶不作", "蛮横无理", "置之不理", "心腹之患", "碧血丹心", "呕心沥血", "心比天高", "风急浪高", "劈风斩浪"], "posx": [5, 2, 3, 4, 5, 3, 5, 7, 0, 3, 5, 6, 7, 8, 0, 1, 2, 3, 7, 0, 4, 5, 6, 7, 0, 6, 6, 4, 5, 6, 7], "posy": [8, 7, 7, 7, 7, 6, 6, 6, 5, 5, 5, 5, 5, 5, 4, 4, 4, 4, 4, 3, 3, 3, 3, 3, 2, 2, 1, 0, 0, 0, 0], "answer": [0, 1, 3, 4, 5, 6, 7, 8, 9, 11, 12, 13, 15, 16, 17, 19, 20, 21, 23, 24, 25, 26, 28, 29, 30], "barrier": []}