{"id": 5529, "word": ["叫", "里", "含", "辛", "茹", "苦", "应", "苞", "连", "外", "宽", "以", "待", "人", "天", "作", "之", "合", "宏", "放", "大", "滥", "量", "才", "录", "用", "职", "篡", "党", "夺", "权"], "idiom": ["里应外合", "天作之合", "叫苦连天", "含辛茹苦", "含苞待放", "宽以待人", "宽宏大量", "量才录用", "滥用职权", "篡党夺权"], "posx": [5, 8, 2, 3, 4, 5, 8, 2, 5, 8, 0, 1, 2, 3, 5, 6, 7, 8, 0, 2, 0, 3, 0, 1, 2, 3, 3, 0, 1, 2, 3], "posy": [8, 8, 7, 7, 7, 7, 7, 6, 6, 6, 5, 5, 5, 5, 5, 5, 5, 5, 4, 4, 3, 3, 2, 2, 2, 2, 1, 0, 0, 0, 0], "answer": [0, 2, 3, 4, 6, 7, 8, 9, 10, 11, 12, 14, 15, 17, 18, 20, 21, 23, 24, 25, 27, 29, 30], "barrier": []}