{"id": 5191, "word": ["金", "鹤", "发", "童", "颜", "玉", "取", "儿", "女", "情", "长", "补", "百", "长", "家", "长", "里", "短", "废", "话", "连", "篇", "常", "俱", "大", "腹", "便", "便", "兴", "论", "饭"], "idiom": ["鹤发童颜", "金童玉女", "儿女情长", "取长补短", "家长里短", "家常便饭", "大腹便便", "长篇大论", "废话连篇", "百废俱兴"], "posx": [6, 4, 5, 6, 7, 6, 8, 5, 6, 7, 8, 8, 0, 3, 5, 6, 7, 8, 0, 1, 2, 3, 5, 0, 3, 4, 5, 6, 0, 3, 5], "posy": [8, 7, 7, 7, 7, 6, 6, 5, 5, 5, 5, 4, 3, 3, 3, 3, 3, 3, 2, 2, 2, 2, 2, 1, 1, 1, 1, 1, 0, 0, 0], "answer": [0, 1, 2, 4, 5, 6, 7, 8, 9, 11, 12, 13, 14, 15, 17, 19, 20, 21, 22, 23, 25, 26, 27, 28, 29], "barrier": []}