{"id": 5704, "word": ["修", "齐", "治", "平", "戴", "心", "比", "天", "高", "静", "帽", "心", "高", "气", "傲", "子", "枕", "哑", "口", "无", "言", "然", "忧", "进", "退", "失", "据", "笑"], "idiom": ["进退失据", "哑然失笑", "哑口无言", "高枕无忧", "心高气傲", "平心静气", "修齐治平", "心比天高", "戴高帽子"], "posx": [2, 3, 4, 5, 8, 5, 6, 7, 8, 5, 8, 3, 4, 5, 6, 8, 4, 2, 3, 4, 5, 2, 4, 0, 1, 2, 3, 2], "posy": [8, 8, 8, 8, 8, 7, 7, 7, 7, 6, 6, 5, 5, 5, 5, 5, 4, 3, 3, 3, 3, 2, 2, 1, 1, 1, 1, 0], "answer": [0, 1, 2, 4, 5, 6, 7, 9, 10, 11, 13, 14, 15, 16, 17, 18, 19, 21, 22, 24, 25, 26], "barrier": []}