{"id": 241, "word": ["忙", "百", "里", "挑", "一", "偷", "决", "胜", "千", "里", "闲", "雌", "锤", "雄", "百", "九", "百", "炼", "成", "钢", "九", "般", "筋", "归", "刁", "铁", "一", "言", "难", "尽", "骨"], "idiom": ["钢筋铁骨", "百炼成钢", "千锤百炼", "决胜千里", "一决雌雄", "百里挑一", "忙里偷闲", "百般刁难", "一言难尽", "九九归一"], "posx": [2, 1, 2, 3, 4, 2, 4, 5, 6, 7, 2, 4, 6, 4, 6, 3, 5, 6, 7, 8, 3, 5, 8, 3, 5, 8, 3, 4, 5, 6, 8], "posy": [8, 7, 7, 7, 7, 6, 6, 6, 6, 6, 5, 5, 5, 4, 4, 3, 3, 3, 3, 3, 2, 2, 2, 1, 1, 1, 0, 0, 0, 0, 0], "answer": [0, 1, 2, 3, 5, 6, 7, 9, 11, 12, 13, 14, 15, 16, 17, 18, 21, 22, 23, 24, 25, 26, 27, 29, 30], "barrier": []}