{"id": 1008, "word": ["人", "忠", "孝", "两", "全", "之", "盘", "好", "常", "乐", "托", "触", "景", "生", "情", "入", "不", "敷", "出", "不", "可", "草", "长", "莺", "飞", "支", "支", "吾", "吾", "蛾", "离", "颠", "扑", "不", "破", "火", "碎"], "idiom": ["触景生情", "好景不长", "草长莺飞", "飞蛾扑火", "颠扑不破", "支离破碎", "支支吾吾", "乐不可支", "入不敷出", "全盘托出", "忠孝两全", "人之常情"], "posx": [3, 5, 6, 7, 8, 3, 8, 1, 3, 6, 8, 0, 1, 2, 3, 5, 6, 7, 8, 1, 6, 0, 1, 2, 3, 5, 6, 7, 8, 3, 5, 2, 3, 4, 5, 3, 5], "posy": [8, 8, 8, 8, 8, 7, 7, 6, 6, 6, 6, 5, 5, 5, 5, 5, 5, 5, 5, 4, 4, 3, 3, 3, 3, 3, 3, 3, 3, 2, 2, 1, 1, 1, 1, 0, 0], "answer": [0, 1, 2, 3, 6, 7, 8, 9, 10, 11, 12, 14, 16, 17, 18, 19, 20, 21, 23, 24, 25, 27, 28, 29, 30, 31, 33, 34, 35], "barrier": []}