{"id": 4314, "word": ["有", "一", "针", "见", "血", "锋", "有", "脱", "相", "肉", "眼", "凡", "胎", "冤", "家", "对", "头", "换", "粉", "身", "碎", "骨", "败", "名", "垂", "千", "古", "山", "崩", "地", "裂"], "idiom": ["针锋相对", "一针见血", "有血有肉", "肉眼凡胎", "脱胎换骨", "粉身碎骨", "身败名裂", "名垂千古", "山崩地裂", "冤家对头"], "posx": [4, 1, 2, 3, 4, 2, 4, 7, 2, 4, 5, 6, 7, 0, 1, 2, 3, 7, 4, 5, 6, 7, 5, 5, 6, 7, 8, 2, 3, 4, 5], "posy": [8, 7, 7, 7, 7, 6, 6, 6, 5, 5, 5, 5, 5, 4, 4, 4, 4, 4, 3, 3, 3, 3, 2, 1, 1, 1, 1, 0, 0, 0, 0], "answer": [0, 1, 2, 3, 5, 6, 7, 8, 9, 10, 11, 13, 14, 16, 17, 18, 20, 21, 22, 23, 25, 26, 27, 28, 30], "barrier": []}