{"id": 2357, "word": ["物", "瞒", "美", "漫", "天", "要", "价", "秉", "过", "廉", "洁", "奉", "公", "名", "扬", "四", "海", "办", "幡", "蛮", "横", "无", "理", "招", "蜂", "引", "蝶", "冲", "魂", "直", "闯"], "idiom": ["蛮横无理", "秉公办理", "廉洁奉公", "物美价廉", "漫天要价", "瞒天过海", "名扬四海", "扬幡招魂", "招蜂引蝶", "横冲直闯"], "posx": [5, 3, 5, 2, 3, 4, 5, 8, 3, 5, 6, 7, 8, 0, 1, 2, 3, 8, 1, 5, 6, 7, 8, 1, 2, 3, 4, 6, 1, 6, 6], "posy": [8, 7, 7, 6, 6, 6, 6, 6, 5, 5, 5, 5, 5, 4, 4, 4, 4, 4, 3, 3, 3, 3, 3, 2, 2, 2, 2, 2, 1, 1, 0], "answer": [0, 2, 3, 4, 5, 7, 8, 9, 10, 11, 14, 15, 16, 17, 18, 19, 21, 22, 24, 25, 26, 27, 28, 29, 30], "barrier": []}