{"id": 4694, "word": ["中", "饱", "私", "囊", "食", "善", "始", "善", "终", "一", "终", "日", "挥", "洒", "自", "如", "而", "一", "走", "了", "之", "日", "就", "月", "将", "马", "纸", "上", "谈", "兵", "任"], "idiom": ["纸上谈兵", "走马上任", "一走了之", "始终如一", "善始善终", "饱食终日", "中饱私囊", "挥洒自如", "一挥而就", "日就月将"], "posx": [5, 6, 7, 8, 6, 3, 4, 5, 6, 1, 4, 6, 1, 2, 3, 4, 1, 4, 5, 6, 7, 0, 1, 2, 3, 5, 4, 5, 6, 7, 5], "posy": [8, 8, 8, 8, 7, 6, 6, 6, 6, 5, 5, 5, 4, 4, 4, 4, 3, 3, 3, 3, 3, 2, 2, 2, 2, 2, 1, 1, 1, 1, 0], "answer": [0, 1, 3, 4, 5, 6, 7, 9, 10, 11, 12, 13, 14, 16, 17, 19, 20, 21, 23, 24, 25, 26, 27, 28, 30], "barrier": []}