{"id": 5745, "word": ["风", "言", "行", "不", "一", "风", "叶", "公", "好", "龙", "语", "知", "事", "秋", "之", "大", "财", "家", "徒", "四", "壁", "江", "洋", "大", "盗", "常", "面", "东", "气", "便", "楚", "去", "粗", "茶", "淡", "饭", "歌"], "idiom": ["四面楚歌", "家徒四壁", "好事之徒", "叶公好龙", "一叶知秋", "言行不一", "风言风语", "家常便饭", "粗茶淡饭", "财大气粗", "江洋大盗", "大江东去"], "posx": [1, 1, 2, 3, 4, 1, 4, 5, 6, 7, 1, 4, 6, 4, 6, 0, 2, 5, 6, 7, 8, 0, 1, 2, 3, 5, 7, 0, 2, 5, 7, 0, 2, 3, 4, 5, 7], "posy": [8, 7, 7, 7, 7, 6, 6, 6, 6, 6, 5, 5, 5, 4, 4, 3, 3, 3, 3, 3, 3, 2, 2, 2, 2, 2, 2, 1, 1, 1, 1, 0, 0, 0, 0, 0, 0], "answer": [0, 2, 3, 4, 5, 7, 8, 9, 10, 11, 12, 13, 14, 15, 16, 17, 19, 20, 21, 22, 24, 25, 26, 27, 28, 29, 30, 32, 33, 34, 35, 36], "barrier": [0, 1, 2, 3, 5, 7, 8, 9, 10, 12, 14, 16, 25, 26, 28, 29, 30, 32, 33, 34, 35, 36]}