{"id": 1575, "word": ["事", "无", "巨", "细", "伤", "大", "肆", "挥", "霍", "温", "文", "儒", "雅", "霍", "故", "无", "知", "谋", "普", "度", "众", "生", "新", "财", "天", "害", "群", "之", "马", "命", "下"], "idiom": ["谋财害命", "害群之马", "普天之下", "普度众生", "挥霍无度", "大肆挥霍", "无伤大雅", "事无巨细", "温文儒雅", "温故知新"], "posx": [2, 3, 4, 5, 3, 3, 4, 5, 6, 0, 1, 2, 3, 5, 0, 5, 0, 2, 4, 5, 6, 7, 0, 2, 4, 2, 3, 4, 5, 2, 4], "posy": [8, 8, 8, 8, 7, 6, 6, 6, 6, 5, 5, 5, 5, 5, 4, 4, 3, 3, 3, 3, 3, 3, 2, 2, 2, 1, 1, 1, 1, 0, 0], "answer": [0, 1, 2, 3, 4, 5, 7, 8, 9, 10, 11, 12, 13, 14, 17, 18, 19, 20, 21, 22, 23, 24, 25, 27, 28, 29, 30], "barrier": [0, 1, 2, 3, 4, 10, 11, 12, 17, 18, 20, 21, 23, 24, 29, 30]}