{"id": 3469, "word": ["取", "心", "而", "不", "平", "起", "平", "坐", "代", "名", "气", "井", "底", "之", "蛙", "一", "团", "和", "气", "观", "文", "天", "女", "散", "花", "娲", "补", "天"], "idiom": ["女娲补天", "天女散花", "坐井观天", "平起平坐", "心平气和", "一团和气", "不名一文", "井底之蛙", "取而代之"], "posx": [7, 2, 7, 0, 2, 3, 4, 5, 7, 0, 2, 5, 6, 7, 8, 0, 1, 2, 3, 5, 0, 5, 6, 7, 8, 6, 6, 6], "posy": [8, 7, 7, 6, 6, 6, 6, 6, 6, 5, 5, 5, 5, 5, 5, 4, 4, 4, 4, 4, 3, 3, 3, 3, 3, 2, 1, 0], "answer": [0, 1, 3, 5, 6, 7, 8, 9, 10, 12, 13, 14, 16, 17, 18, 19, 20, 21, 23, 24, 25, 26, 27], "barrier": []}