{"id": 4594, "word": ["风", "冷", "审", "己", "度", "人", "语", "时", "翩", "手", "冰", "度", "翩", "翩", "起", "舞", "人", "多", "势", "众", "足", "循", "规", "蹈", "矩", "环", "无", "往", "不", "利", "复"], "idiom": ["人多势众", "审时度势", "审己度人", "风度翩翩", "翩翩起舞", "手舞足蹈", "循规蹈矩", "循环往复", "无往不利", "冷语冰人"], "posx": [4, 0, 2, 3, 4, 5, 0, 2, 4, 7, 0, 2, 4, 5, 6, 7, 0, 1, 2, 3, 7, 5, 6, 7, 8, 5, 4, 5, 6, 7, 5], "posy": [8, 7, 7, 7, 7, 7, 6, 6, 6, 6, 5, 5, 5, 5, 5, 5, 4, 4, 4, 4, 4, 3, 3, 3, 3, 2, 1, 1, 1, 1, 0], "answer": [0, 1, 2, 3, 5, 6, 8, 9, 10, 11, 12, 13, 14, 17, 18, 19, 20, 21, 22, 23, 25, 26, 28, 29, 30], "barrier": []}