{"id": 5780, "word": ["狭", "路", "相", "逢", "人", "命", "关", "天", "凶", "门", "变", "化", "无", "穷", "大", "吉", "凶", "多", "吉", "少", "极", "十", "恶", "不", "赦", "拿", "九", "安", "安", "稳", "稳"], "idiom": ["安安稳稳", "十拿九稳", "十恶不赦", "穷凶极恶", "变化无穷", "逢凶化吉", "狭路相逢", "凶多吉少", "关门大吉", "人命关天"], "posx": [0, 1, 2, 3, 5, 6, 7, 8, 3, 7, 2, 3, 4, 5, 7, 3, 5, 6, 7, 8, 5, 4, 5, 6, 7, 4, 4, 2, 3, 4, 5], "posy": [8, 8, 8, 8, 8, 8, 8, 8, 7, 7, 6, 6, 6, 6, 6, 5, 5, 5, 5, 5, 4, 3, 3, 3, 3, 2, 1, 0, 0, 0, 0], "answer": [2, 3, 4, 5, 8, 12, 13, 14, 18, 19, 20, 23, 24, 26, 29, 30], "barrier": []}