{"id": 4976, "word": ["穷", "好", "骄", "奢", "淫", "逸", "极", "恶", "查", "欲", "劳", "而", "无", "功", "恼", "实", "闭", "月", "羞", "花", "引", "经", "据", "典", "关", "成", "火", "锁", "怒", "火", "中", "烧", "国", "身", "败", "名", "裂"], "idiom": ["穷奢极欲", "骄奢淫逸", "好逸恶劳", "劳而无功", "查无实据", "引经据典", "引火烧身", "怒火中烧", "恼羞成怒", "闭月羞花", "闭关锁国", "身败名裂"], "posx": [3, 5, 2, 3, 4, 5, 3, 5, 7, 3, 5, 6, 7, 8, 2, 7, 0, 1, 2, 3, 5, 6, 7, 8, 0, 2, 5, 0, 2, 3, 4, 5, 0, 5, 6, 7, 8], "posy": [8, 8, 7, 7, 7, 7, 6, 6, 6, 5, 5, 5, 5, 5, 4, 4, 3, 3, 3, 3, 3, 3, 3, 3, 2, 2, 2, 1, 1, 1, 1, 1, 0, 0, 0, 0, 0], "answer": [1, 2, 3, 4, 6, 7, 8, 9, 10, 11, 12, 14, 15, 16, 17, 19, 20, 21, 23, 24, 25, 26, 28, 29, 30, 32, 33, 34, 36], "barrier": []}