{"id": 1775, "word": ["以", "德", "服", "人", "九", "丁", "九", "败", "兴", "而", "归", "语", "旺", "一", "览", "无", "遗", "伦", "妙", "三", "番", "两", "次", "不", "言", "败", "可", "两", "俱", "豪", "言", "壮", "语", "伤"], "idiom": ["妙不可言", "豪言壮语", "三言两语", "三番两次", "语无伦次", "一览无遗", "九九归一", "败兴而归", "人丁兴旺", "以德服人", "两败俱伤"], "posx": [0, 1, 2, 3, 5, 3, 5, 2, 3, 4, 5, 7, 3, 5, 6, 7, 8, 7, 2, 4, 5, 6, 7, 2, 4, 6, 2, 4, 6, 1, 2, 3, 4, 6], "posy": [8, 8, 8, 8, 8, 7, 7, 6, 6, 6, 6, 6, 5, 5, 5, 5, 5, 4, 3, 3, 3, 3, 3, 2, 2, 2, 1, 1, 1, 0, 0, 0, 0, 0], "answer": [0, 1, 2, 3, 4, 6, 7, 8, 9, 10, 11, 12, 13, 14, 15, 16, 18, 19, 20, 21, 22, 23, 24, 25, 26, 27, 28, 29, 30, 31], "barrier": [0, 1, 2, 4, 6, 7, 9, 10, 13, 14, 16, 18, 19, 20, 23, 24, 26, 27]}