{"id": 223, "word": ["排", "飞", "沙", "走", "石", "五", "简", "讷", "脏", "金", "口", "玉", "言", "六", "敏", "肺", "腑", "之", "言", "言", "行", "不", "一", "传", "不", "了", "身", "不", "由", "己", "百", "孺", "子", "可", "教", "衷", "了"], "idiom": ["一了百了", "言行不一", "讷言敏行", "金口玉言", "排沙简金", "飞沙走石", "言不由衷", "身不由己", "言传身教", "肺腑之言", "五脏六腑", "孺子可教"], "posx": [3, 2, 3, 4, 5, 1, 3, 6, 1, 3, 4, 5, 6, 1, 6, 0, 1, 2, 3, 5, 6, 7, 8, 3, 5, 8, 3, 4, 5, 6, 8, 0, 1, 2, 3, 5, 8], "posy": [8, 7, 7, 7, 7, 6, 6, 6, 5, 5, 5, 5, 5, 4, 4, 3, 3, 3, 3, 3, 3, 3, 3, 2, 2, 2, 1, 1, 1, 1, 1, 0, 0, 0, 0, 0, 0], "answer": [0, 1, 2, 3, 5, 7, 8, 9, 10, 11, 13, 14, 15, 17, 18, 19, 20, 21, 23, 24, 25, 27, 28, 29, 30, 31, 32, 34, 36], "barrier": []}