{"id": 148, "word": ["身", "汗", "流", "浃", "背", "铁", "单", "枪", "匹", "马", "证", "力", "功", "急", "如", "履", "薄", "冰", "劳", "苦", "功", "高", "山", "事", "近", "灿", "出", "师", "不", "利", "若", "有", "若", "无", "繁", "奈", "星"], "idiom": ["汗流浃背", "汗马功劳", "单枪匹马", "身单力薄", "如履薄冰", "铁证如山", "劳苦功高", "急功近利", "出师不利", "事出无奈", "若有若无", "灿若繁星"], "posx": [2, 5, 6, 7, 8, 0, 2, 3, 4, 5, 0, 2, 5, 7, 0, 1, 2, 3, 5, 6, 7, 8, 0, 4, 7, 1, 4, 5, 6, 7, 1, 2, 3, 4, 1, 4, 1], "posy": [8, 8, 8, 8, 8, 7, 7, 7, 7, 7, 6, 6, 6, 6, 5, 5, 5, 5, 5, 5, 5, 5, 4, 4, 4, 3, 3, 3, 3, 3, 2, 2, 2, 2, 1, 1, 0], "answer": [0, 1, 2, 3, 5, 7, 8, 9, 10, 11, 12, 15, 16, 17, 19, 20, 21, 22, 23, 24, 25, 27, 28, 29, 31, 32, 33, 34, 35, 36], "barrier": []}