{"id": 4354, "word": ["苟", "穷", "且", "益", "坚", "仪", "一", "偷", "态", "触", "景", "生", "情", "万", "即", "不", "千", "钧", "一", "发", "自", "刀", "弱", "不", "禁", "风", "三", "三", "两", "两", "断"], "idiom": ["三三两两", "一刀两断", "千钧一发", "一触即发", "触景生情", "苟且偷生", "穷且益坚", "情不自禁", "弱不禁风", "仪态万千"], "posx": [5, 4, 5, 6, 7, 0, 3, 5, 0, 3, 4, 5, 6, 0, 3, 6, 0, 1, 2, 3, 6, 2, 4, 5, 6, 7, 0, 1, 2, 3, 2], "posy": [8, 7, 7, 7, 7, 6, 6, 6, 5, 5, 5, 5, 5, 4, 4, 4, 3, 3, 3, 3, 3, 2, 2, 2, 2, 2, 1, 1, 1, 1, 0], "answer": [0, 1, 2, 4, 5, 6, 8, 10, 11, 12, 14, 15, 16, 18, 19, 20, 21, 22, 23, 25, 26, 28, 29, 30], "barrier": []}