{"id": 690, "word": ["悲", "欢", "离", "合", "曾", "几", "何", "时", "喜", "不", "白", "之", "冤", "将", "再", "家", "信", "手", "拈", "来", "建", "将", "轻", "功", "成", "名", "就", "疑", "怕", "立", "副", "重", "操", "旧", "业", "其", "实"], "idiom": ["名副其实", "功成名就", "建功立业", "重操旧业", "拈轻怕重", "信手拈来", "时不再来", "曾几何时", "不白之冤", "欢喜冤家", "悲欢离合", "将信将疑"], "posx": [5, 6, 7, 8, 0, 1, 2, 3, 6, 3, 4, 5, 6, 0, 3, 6, 0, 1, 2, 3, 5, 0, 2, 5, 6, 7, 8, 0, 2, 5, 7, 2, 3, 4, 5, 7, 7], "posy": [8, 8, 8, 8, 7, 7, 7, 7, 7, 6, 6, 6, 6, 5, 5, 5, 4, 4, 4, 4, 4, 3, 3, 3, 3, 3, 3, 2, 2, 2, 2, 1, 1, 1, 1, 1, 0], "answer": [1, 7, 9, 12, 16, 18, 23, 25, 31, 34], "barrier": []}