{"id": 2331, "word": ["公", "私", "兼", "顾", "名", "饮", "水", "思", "源", "声", "食", "义", "东", "山", "再", "起", "河", "击", "居", "心", "不", "良", "东", "跑", "西", "颠", "口", "狮", "大", "逆", "不", "道", "吼", "一"], "idiom": ["大逆不道", "心口不一", "居心不良", "饮食起居", "饮水思源", "顾名思义", "公私兼顾", "东山再起", "声东击西", "东跑西颠", "河东狮吼"], "posx": [4, 5, 6, 7, 7, 5, 6, 7, 8, 2, 5, 7, 2, 3, 4, 5, 0, 2, 5, 6, 7, 8, 0, 1, 2, 3, 6, 0, 4, 5, 6, 7, 0, 6], "posy": [8, 8, 8, 8, 7, 6, 6, 6, 6, 5, 5, 5, 4, 4, 4, 4, 3, 3, 3, 3, 3, 3, 2, 2, 2, 2, 2, 1, 1, 1, 1, 1, 0, 0], "answer": [0, 1, 2, 4, 5, 6, 7, 9, 10, 11, 12, 13, 14, 16, 17, 18, 20, 21, 22, 23, 25, 26, 27, 28, 29, 30, 31, 32, 33], "barrier": []}