{"id": 3419, "word": ["明", "辨", "是", "非", "明", "白", "白", "日", "做", "梦", "龙", "白", "贼", "鱼", "心", "服", "口", "服", "虚", "诛", "繁", "背", "梦", "笔", "生", "花", "井", "伐", "似", "离", "衣", "锦", "还", "乡"], "idiom": ["背井离乡", "衣锦还乡", "繁花似锦", "梦笔生花", "口诛笔伐", "心服口服", "做贼心虚", "白日做梦", "明明白白", "明辨是非", "白龙鱼服"], "posx": [0, 1, 2, 3, 0, 5, 0, 1, 2, 3, 5, 0, 2, 5, 2, 3, 4, 5, 2, 4, 6, 8, 3, 4, 5, 6, 8, 4, 6, 8, 5, 6, 7, 8], "posy": [8, 8, 8, 8, 7, 7, 6, 6, 6, 6, 6, 5, 5, 5, 4, 4, 4, 4, 3, 3, 3, 3, 2, 2, 2, 2, 2, 1, 1, 1, 0, 0, 0, 0], "answer": [0, 1, 2, 4, 5, 7, 8, 9, 10, 11, 12, 15, 16, 17, 18, 19, 20, 21, 22, 24, 25, 27, 29, 30, 31, 33], "barrier": []}