{"id": 310, "word": ["史", "后", "会", "无", "期", "前", "先", "军", "例", "行", "公", "事", "令", "人", "神", "往", "后", "如", "魂", "不", "徇", "私", "情", "山", "颠", "倒", "黑", "白", "倒", "之", "欢", "喜", "冤", "家"], "idiom": ["后会无期", "史无前例", "例行公事", "先公后私", "不徇私情", "不白之冤", "颠倒黑白", "神魂颠倒", "令人神往", "军令如山", "欢喜冤家"], "posx": [5, 3, 4, 5, 6, 5, 7, 0, 5, 6, 7, 8, 0, 1, 2, 3, 7, 0, 2, 5, 6, 7, 8, 0, 2, 3, 4, 5, 2, 5, 3, 4, 5, 6], "posy": [8, 7, 7, 7, 7, 6, 6, 5, 5, 5, 5, 5, 4, 4, 4, 4, 4, 3, 3, 3, 3, 3, 3, 2, 2, 2, 2, 2, 1, 1, 0, 0, 0, 0], "answer": [3, 8, 10, 12, 14, 21, 24, 27, 32], "barrier": []}